botwit/__init__.py
botwit/__main__.py
botwit/app.py
botwit/config.py
botwit/py.typed
botwit/sync_memo.py
botwit/twitter_client.py
botwit-0.2.2.dist-info/METADATA
botwit-0.2.2.dist-info/WHEEL
botwit-0.2.2.dist-info/entry_points.txt
botwit-0.2.2.dist-info/licenses/LICENSE
botwit-0.2.2.dist-info/RECORD
