Metadata-Version: 2.1
Name: botwit
Version: 0.2.2
Summary: My Twitter Bot.
Author-email: gjeusel <gjeusel@gmail.com>
License-File: LICENSE
Classifier: Intended Audience :: Developers
Classifier: Natural Language :: English
Classifier: Programming Language :: Python
Classifier: Programming Language :: Python :: 3
Classifier: Programming Language :: Python :: 3.10
Classifier: Programming Language :: Python :: 3.11
Classifier: Topic :: Software Development
Requires-Python: >=3.10
Requires-Dist: httpx-auth==0.15.*
Requires-Dist: httpx==0.23.*
Requires-Dist: notion-client==2.0.0
Requires-Dist: pydantic[dotenv]
Requires-Dist: pytz
Requires-Dist: starlette
Requires-Dist: structlog
Requires-Dist: typer
Requires-Dist: uvicorn[standard]
Provides-Extra: all
Requires-Dist: botwit[dev]; extra == 'all'
Requires-Dist: botwit[doc]; extra == 'all'
Provides-Extra: dev
Requires-Dist: black==22.10.*; extra == 'dev'
Requires-Dist: cookiecutter; extra == 'dev'
Requires-Dist: coverage[toml]<7.0,>=6.5.0; extra == 'dev'
Requires-Dist: cruft; extra == 'dev'
Requires-Dist: mypy==0.991; extra == 'dev'
Requires-Dist: pdbpp; extra == 'dev'
Requires-Dist: pip-tools; extra == 'dev'
Requires-Dist: pre-commit==2.20.*; extra == 'dev'
Requires-Dist: ptpython; extra == 'dev'
Requires-Dist: pytest-mock==3.10.*; extra == 'dev'
Requires-Dist: pytest-sugar==0.9.*; extra == 'dev'
Requires-Dist: pytest==7.1.*; extra == 'dev'
Requires-Dist: rich; extra == 'dev'
Requires-Dist: ruff; extra == 'dev'
Requires-Dist: types-pytz; extra == 'dev'
Requires-Dist: typing-extensions; extra == 'dev'
Requires-Dist: vcrpy==4.2.*; extra == 'dev'
Provides-Extra: doc
Requires-Dist: markdown-include; extra == 'doc'
Requires-Dist: mdx-truly-sane-lists; extra == 'doc'
Requires-Dist: mkdocs; extra == 'doc'
Requires-Dist: mkdocs-exclude; extra == 'doc'
Requires-Dist: mkdocs-material; extra == 'doc'
Requires-Dist: mkdocstrings[python]; extra == 'doc'
